lebai/__init__.py
lebai/lebai_http_service.py
lebai/robot.py
lebai/scene.py
lebai/type.py
lebai/pb2/__init__.py
lebai/pb2/messages_pb2.py
lebai/pb2/messages_pb2_grpc.py
lebai/pb2/os_server_pb2.py
lebai/pb2/os_server_pb2_grpc.py
lebai/pb2/private_controller_pb2.py
lebai/pb2/private_controller_pb2_grpc.py
lebai/pb2/robot_controller_pb2.py
lebai/pb2/robot_controller_pb2_grpc.py
lebai/pb2/robot_test_pb2.py
lebai/pb2/robot_test_pb2_grpc.py
lebai/pb2/simulation_pb2.py
lebai/pb2/simulation_pb2_grpc.py
lebai-0.9.0.dist-info/LICENSE
lebai-0.9.0.dist-info/METADATA
lebai-0.9.0.dist-info/WHEEL
lebai-0.9.0.dist-info/top_level.txt
lebai-0.9.0.dist-info/RECORD
