Metadata-Version: 2.1
Name: lebai
Version: 0.9.0
Summary: Lebai Robot Python SDK
Home-page: https://github.com/lebai-robotics/lebai-python-sdk
Author: rozow
Author-email: rongzong123@foxmail.com
Classifier: Programming Language :: Python :: 3
Classifier: License :: OSI Approved :: MIT License
Classifier: Operating System :: OS Independent
Requires-Python: >=3.7
License-File: LICENSE
Requires-Dist: grpcio
Requires-Dist: protobuf (~=3.19.4)
Requires-Dist: requests
